audio_dsp/__init__.py
audio_dsp/effects/LP_BP_filter.py
audio_dsp/effects/__init__.py
audio_dsp/effects/audio_to_image_effects.py
audio_dsp/effects/auto_tune.py
audio_dsp/effects/convolution_reverb.py
audio_dsp/effects/distortion.py
audio_dsp/effects/fractional_calculus_compressor.py
audio_dsp/effects/frequency_splicer.py
audio_dsp/effects/glitch.py
audio_dsp/effects/lofi.py
audio_dsp/effects/melt_spectrum.py
audio_dsp/effects/multi_band_saturation.py
audio_dsp/effects/negative_audio.py
audio_dsp/effects/phaser.py
audio_dsp/effects/pitch_drift.py
audio_dsp/effects/pitch_flutter.py
audio_dsp/effects/random_chorus.py
audio_dsp/effects/sitar_sympathetic_resonance.py
audio_dsp/effects/spectral_flow_compressor.py
audio_dsp/effects/spectral_quantization.py
audio_dsp/effects/super_clean_compressor.py
audio_dsp/effects/super_delay.py
audio_dsp/effects/tape_saturation.py
audio_dsp/effects/temporal_gravity_warp.py
audio_dsp/effects/time_slice.py
audio_dsp/effects/topological_dynamics_compressor.py
audio_dsp/effects/variable_quantizer.py
audio_dsp/effects/vocoder.py
audio_dsp/effects/impulse_response/3000CStreetGarageStairwell.wav
audio_dsp/midi/__init__.py
audio_dsp/midi/midi_loop.wav
audio_dsp/midi/midi_looper.py
audio_dsp/midi/polyrhythmic_midi.py
audio_dsp/midi/logarithmic_tunings/logarithmic_tunings.py
audio_dsp/midi/logarithmic_tunings/test.mid
audio_dsp/midi/midi_files/can1.mid
audio_dsp/midi/midi_files/can2.mid
audio_dsp/midi/midi_files/can3.mid
audio_dsp/midi/midi_files/can4.mid
audio_dsp/midi/midi_files/cnt1.mid
audio_dsp/midi/midi_files/cnt2.mid
audio_dsp/midi/midi_files/cnt3.mid
audio_dsp/midi/midi_files/dou1.mid
audio_dsp/midi/midi_files/dou2.mid
audio_dsp/midi/midi_files/inver1.mid
audio_dsp/midi/midi_files/inver2.mid
audio_dsp/midi/midi_files/mir1.mid
audio_dsp/midi/midi_files/mir2.mid
audio_dsp/midi/midi_files/reg1.mid
audio_dsp/midi/midi_files/reg2.mid
audio_dsp/midi/midi_files/tri1.mid
audio_dsp/midi/midi_files/tri2.mid
audio_dsp/midi/midi_files/unfin.mid
audio_dsp-0.1.10.dist-info/LICENSE
audio_dsp-0.1.10.dist-info/METADATA
audio_dsp-0.1.10.dist-info/WHEEL
audio_dsp-0.1.10.dist-info/top_level.txt
audio_dsp-0.1.10.dist-info/RECORD
