Metadata-Version: 2.1
Name: audio-dsp
Version: 0.1.10
Summary: Python audio DSP library for synthesis, effects, and sequencing
Author: Dominique Grys
License: MIT
Project-URL: Homepage, https://github.com/Metallicode/python_audio_dsp
Project-URL: Repository, https://github.com/Metallicode/python_audio_dsp
Project-URL: Issues, https://github.com/Metallicode/python_audio_dsp/issues
Keywords: audio,dsp,synthesis,effects,music,signal-processing
Classifier: Development Status :: 4 - Beta
Classifier: Intended Audience :: Developers
Classifier: Intended Audience :: Science/Research
Classifier: License :: OSI Approved :: MIT License
Classifier: Operating System :: OS Independent
Classifier: Programming Language :: Python :: 3
Classifier: Programming Language :: Python :: 3.8
Classifier: Programming Language :: Python :: 3.9
Classifier: Programming Language :: Python :: 3.10
Classifier: Programming Language :: Python :: 3.11
Classifier: Programming Language :: Python :: 3.12
Classifier: Topic :: Multimedia :: Sound/Audio
Classifier: Topic :: Multimedia :: Sound/Audio :: Sound Synthesis
Classifier: Topic :: Scientific/Engineering
Requires-Python: >=3.8
License-File: LICENSE
Requires-Dist: numpy>=1.20.0
Requires-Dist: scipy>=1.7.0
Requires-Dist: soundfile>=0.10.0
Provides-Extra: audio
Requires-Dist: librosa>=0.9.0; extra == "audio"
Requires-Dist: pydub>=0.25.0; extra == "audio"
Requires-Dist: simpleaudio>=1.0.0; extra == "audio"
Provides-Extra: full
Requires-Dist: librosa>=0.9.0; extra == "full"
Requires-Dist: mido>=1.2.0; extra == "full"
Requires-Dist: matplotlib>=3.0.0; extra == "full"
Requires-Dist: pydub>=0.25.0; extra == "full"
Requires-Dist: simpleaudio>=1.0.0; extra == "full"
Requires-Dist: scikit-learn>=1.0.0; extra == "full"
Requires-Dist: opencv-python>=4.0.0; extra == "full"
Requires-Dist: Pillow>=8.0.0; extra == "full"
Requires-Dist: noise>=1.2.0; extra == "full"
Requires-Dist: sympy>=1.9.0; extra == "full"
Provides-Extra: midi
Requires-Dist: mido>=1.2.0; extra == "midi"
Provides-Extra: ml
Requires-Dist: scikit-learn>=1.0.0; extra == "ml"
Requires-Dist: umap-learn>=0.5.0; extra == "ml"
Provides-Extra: synth
Requires-Dist: soundfile>=0.10.0; extra == "synth"
Provides-Extra: viz
Requires-Dist: matplotlib>=3.0.0; extra == "viz"
